wxyz/notebooks/Utils.ipynb
wxyz/notebooks/__init__.py
wxyz/notebooks/_version.py
wxyz/notebooks/index.ipynb
wxyz/notebooks/API/JSON Schema Form.ipynb
wxyz/notebooks/API/JSON-LD.ipynb
wxyz/notebooks/API/JSON.ipynb
wxyz/notebooks/API/__init__.py
wxyz/notebooks/Design/Tribbles.ipynb
wxyz/notebooks/Design/__init__.py
wxyz/notebooks/Design/DVCS/App.ipynb
wxyz/notebooks/Design/DVCS/Simple Example.ipynb
wxyz/notebooks/Design/DVCS/index.ipynb
wxyz/notebooks/Examples/DataGrid.ipynb
wxyz/notebooks/Examples/Dock Panel.ipynb
wxyz/notebooks/Examples/Editor.ipynb
wxyz/notebooks/Examples/Filing.ipynb
wxyz/notebooks/Examples/Full Screen.ipynb
wxyz/notebooks/Examples/Git I.ipynb
wxyz/notebooks/Examples/Git II.ipynb
wxyz/notebooks/Examples/Git III.ipynb
wxyz/notebooks/Examples/Hello Worlds.ipynb
wxyz/notebooks/Examples/JSON Schema Form.ipynb
wxyz/notebooks/Examples/JSON Tricks.ipynb
wxyz/notebooks/Examples/JSON-E.ipynb
wxyz/notebooks/Examples/JSON-LD Playground.ipynb
wxyz/notebooks/Examples/SVG.ipynb
wxyz/notebooks/Examples/SelectGrid.ipynb
wxyz/notebooks/Examples/StyleGrid I.ipynb
wxyz/notebooks/Examples/StyleGrid II.ipynb
wxyz/notebooks/Examples/TPOTWXYZ.ipynb
wxyz/notebooks/Examples/Terminal.ipynb
wxyz/notebooks/Examples/__init__.py
wxyz/notebooks/Examples/example.svg
wxyz/notebooks/js/LICENSE.txt
wxyz/notebooks/js/package.json
wxyz_notebooks-0.5.1.dist-info/LICENSE.txt
wxyz_notebooks-0.5.1.dist-info/METADATA
wxyz_notebooks-0.5.1.dist-info/WHEEL
wxyz_notebooks-0.5.1.dist-info/top_level.txt
wxyz_notebooks-0.5.1.dist-info/RECORD
