Metadata-Version: 2.1
Name: wxyz-notebooks
Version: 0.5.1
Summary: notebook demos for experimental Jupyter widgets
Home-page: https://deathbeds.github.io/wxyz
Author: wxyz contributors
Author-email: ripxl@googlegroups.com
License: BSD-3-Clause
Project-URL: Bug Tracker, https://github.com/deathbeds/wxyz/issues
Project-URL: Changelog, https://github.com/deathbeds/wxyz/blob/master/CHANGELOG.md
Project-URL: CI, https://dev.azure.com/nickbollweg/deathbeds/_build/latest?definitionId=6&branchName=master
Project-URL: Documentation, https://deathbeds.github.io/wxyz
Project-URL: Releases, https://github.com/deathbeds/wxyz/releases
Project-URL: Source Code, https://github.com/deathbeds/wxyz
Keywords: Interactive
Platform: UNKNOWN
Classifier: Framework :: Jupyter
Classifier: Intended Audience :: Developers
Classifier: Intended Audience :: Information Technology
Classifier: License :: OSI Approved :: BSD License
Classifier: Programming Language :: Python
Requires-Python: >=3.7
License-File: src/wxyz/notebooks/js/LICENSE.txt
Requires-Dist: wxyz-core (<0.6,>=0.5)
Requires-Dist: wxyz-datagrid (<0.6,>=0.5)
Requires-Dist: wxyz-dvcs (<0.6,>=0.5)
Requires-Dist: wxyz-html (<0.6,>=0.5)
Requires-Dist: wxyz-json-e (<0.6,>=0.5)
Requires-Dist: wxyz-json-schema-form (<0.6,>=0.5)
Requires-Dist: wxyz-jsonld (<0.6,>=0.5)
Requires-Dist: wxyz-lab (<0.6,>=0.5)
Requires-Dist: wxyz-svg (<0.6,>=0.5)
Requires-Dist: wxyz-tpl-jinja (<0.6,>=0.5)
Requires-Dist: wxyz-yaml (<0.6,>=0.5)
Provides-Extra: all
Requires-Dist: importnb ; extra == 'all'
Requires-Dist: cycler ; extra == 'all'
Requires-Dist: dask ; extra == 'all'
Requires-Dist: dask-labextension ; extra == 'all'
Requires-Dist: dask-ml ; extra == 'all'
Requires-Dist: distributed ; extra == 'all'
Requires-Dist: ipympl ; extra == 'all'
Requires-Dist: lime ; extra == 'all'
Requires-Dist: matplotlib ; extra == 'all'
Requires-Dist: scikit-image ; extra == 'all'
Requires-Dist: skikit-learn ; extra == 'all'
Requires-Dist: scikit-mdr ; extra == 'all'
Requires-Dist: skrebate ; extra == 'all'
Requires-Dist: tpot ; extra == 'all'
Requires-Dist: umap-learn ; extra == 'all'
Requires-Dist: yellowbrick ; extra == 'all'
Requires-Dist: bqplot ; extra == 'all'
Requires-Dist: datashader ; extra == 'all'
Requires-Dist: hvplot ; extra == 'all'
Requires-Dist: ipylab ; extra == 'all'
Provides-Extra: binder
Requires-Dist: importnb ; extra == 'binder'
Requires-Dist: cycler ; extra == 'binder'
Requires-Dist: dask ; extra == 'binder'
Requires-Dist: dask-labextension ; extra == 'binder'
Requires-Dist: dask-ml ; extra == 'binder'
Requires-Dist: distributed ; extra == 'binder'
Requires-Dist: ipympl ; extra == 'binder'
Requires-Dist: lime ; extra == 'binder'
Requires-Dist: matplotlib ; extra == 'binder'
Requires-Dist: scikit-image ; extra == 'binder'
Requires-Dist: skikit-learn ; extra == 'binder'
Requires-Dist: scikit-mdr ; extra == 'binder'
Requires-Dist: skrebate ; extra == 'binder'
Requires-Dist: tpot ; extra == 'binder'
Requires-Dist: umap-learn ; extra == 'binder'
Requires-Dist: yellowbrick ; extra == 'binder'
Provides-Extra: tests
Requires-Dist: pytest ; extra == 'tests'
Provides-Extra: thirdparty
Requires-Dist: bqplot ; extra == 'thirdparty'
Requires-Dist: datashader ; extra == 'thirdparty'
Requires-Dist: hvplot ; extra == 'thirdparty'
Requires-Dist: ipylab ; extra == 'thirdparty'
